{
  "info": {
    "title": "Pacha Claim Core",
    "version": "0.1.0"
  },
  "openapi": "3.1.0",
  "paths": {
    "/console/claims/{claim_id}/projections": {
      "get": {
        "operationId": "list_projections_console_claims__claim_id__projections_get",
        "parameters": [
          {
            "in": "path",
            "name": "claim_id",
            "required": true,
            "schema": {
              "title": "Claim Id",
              "type": "string"
            }
          },
          {
            "in": "header",
            "name": "X-Actor",
            "required": true,
            "schema": {
              "title": "X-Actor",
              "type": "string"
            }
          }
        ],
        "responses": {
          "200": {
            "content": {
              "application/json": {
                "schema": {}
              }
            },
            "description": "Successful Response"
          },
          "422": {
            "content": {
              "application/json": {
                "schema": {
                  "$ref": "#/components/schemas/HTTPValidationError"
                }
              }
            },
            "description": "Validation Error"
          }
        },
        "summary": "List Projections"
      }
    },
    "/console/claims/{claim_id}/projections/{projection_id}/paste-assist": {
      "get": {
        "operationId": "read_paste_assist_console_claims__claim_id__projections__projection_id__paste_assist_get",
        "parameters": [
          {
            "in": "path",
            "name": "claim_id",
            "required": true,
            "schema": {
              "title": "Claim Id",
              "type": "string"
            }
          },
          {
            "in": "path",
            "name": "projection_id",
            "required": true,
            "schema": {
              "title": "Projection Id",
              "type": "string"
            }
          },
          {
            "in": "header",
            "name": "X-Actor",
            "required": true,
            "schema": {
              "title": "X-Actor",
              "type": "string"
            }
          }
        ],
        "responses": {
          "200": {
            "content": {
              "application/json": {
                "schema": {}
              }
            },
            "description": "Successful Response"
          },
          "422": {
            "content": {
              "application/json": {
                "schema": {
                  "$ref": "#/components/schemas/HTTPValidationError"
                }
              }
            },
            "description": "Validation Error"
          }
        },
        "summary": "Read Paste Assist"
      }
    },
    "/console/claims/{claim_id}/projections/{projection_id}/paste-assist/confirm": {
      "post": {
        "operationId": "confirm_paste_assist_console_claims__claim_id__projections__projection_id__paste_assist_confirm_post",
        "parameters": [
          {
            "in": "path",
            "name": "claim_id",
            "required": true,
            "schema": {
              "title": "Claim Id",
              "type": "string"
            }
          },
          {
            "in": "path",
            "name": "projection_id",
            "required": true,
            "schema": {
              "title": "Projection Id",
              "type": "string"
            }
          },
          {
            "in": "header",
            "name": "X-Actor",
            "required": true,
            "schema": {
              "title": "X-Actor",
              "type": "string"
            }
          },
          {
            "in": "header",
            "name": "Idempotency-Key",
            "required": true,
            "schema": {
              "title": "Idempotency-Key",
              "type": "string"
            }
          }
        ],
        "requestBody": {
          "content": {
            "application/json": {
              "schema": {
                "$ref": "#/components/schemas/ConfirmRequest"
              }
            }
          },
          "required": true
        },
        "responses": {
          "200": {
            "content": {
              "application/json": {
                "schema": {}
              }
            },
            "description": "Successful Response"
          },
          "422": {
            "content": {
              "application/json": {
                "schema": {
                  "$ref": "#/components/schemas/HTTPValidationError"
                }
              }
            },
            "description": "Validation Error"
          }
        },
        "summary": "Confirm Paste Assist"
      }
    },
    "/console/claims/{claim_id}/projections/{projection_id}/paste-assist/groups/{group_id}": {
      "put": {
        "operationId": "update_group_console_claims__claim_id__projections__projection_id__paste_assist_groups__group_id__put",
        "parameters": [
          {
            "in": "path",
            "name": "claim_id",
            "required": true,
            "schema": {
              "title": "Claim Id",
              "type": "string"
            }
          },
          {
            "in": "path",
            "name": "projection_id",
            "required": true,
            "schema": {
              "title": "Projection Id",
              "type": "string"
            }
          },
          {
            "in": "path",
            "name": "group_id",
            "required": true,
            "schema": {
              "title": "Group Id",
              "type": "string"
            }
          },
          {
            "in": "header",
            "name": "X-Actor",
            "required": true,
            "schema": {
              "title": "X-Actor",
              "type": "string"
            }
          }
        ],
        "requestBody": {
          "content": {
            "application/json": {
              "schema": {
                "$ref": "#/components/schemas/GroupUpdate"
              }
            }
          },
          "required": true
        },
        "responses": {
          "200": {
            "content": {
              "application/json": {
                "schema": {}
              }
            },
            "description": "Successful Response"
          },
          "422": {
            "content": {
              "application/json": {
                "schema": {
                  "$ref": "#/components/schemas/HTTPValidationError"
                }
              }
            },
            "description": "Validation Error"
          }
        },
        "summary": "Update Group"
      }
    },
    "/console/claims/{claim_id}/projections/{projection_id}/paste-assist/start": {
      "post": {
        "operationId": "start_paste_assist_console_claims__claim_id__projections__projection_id__paste_assist_start_post",
        "parameters": [
          {
            "in": "path",
            "name": "claim_id",
            "required": true,
            "schema": {
              "title": "Claim Id",
              "type": "string"
            }
          },
          {
            "in": "path",
            "name": "projection_id",
            "required": true,
            "schema": {
              "title": "Projection Id",
              "type": "string"
            }
          },
          {
            "in": "header",
            "name": "X-Actor",
            "required": true,
            "schema": {
              "title": "X-Actor",
              "type": "string"
            }
          }
        ],
        "responses": {
          "200": {
            "content": {
              "application/json": {
                "schema": {}
              }
            },
            "description": "Successful Response"
          },
          "422": {
            "content": {
              "application/json": {
                "schema": {
                  "$ref": "#/components/schemas/HTTPValidationError"
                }
              }
            },
            "description": "Validation Error"
          }
        },
        "summary": "Start Paste Assist"
      }
    }
  }
}
